README.md
setup.py
cellar/__init__.py
cellar/__main__.py
cellar/__version__.py
cellar/cli.py
cellar/crypt.py
cellar/log.py
pynacl_cellar.egg-info/PKG-INFO
pynacl_cellar.egg-info/SOURCES.txt
pynacl_cellar.egg-info/dependency_links.txt
pynacl_cellar.egg-info/entry_points.txt
pynacl_cellar.egg-info/requires.txt
pynacl_cellar.egg-info/top_level.txt