Metadata-Version: 2.1
Name: pynacl-cellar
Version: 0.1.0
Summary: Uses libsodium for symetric, secret key encryption of files and folders
Author: Justin Quick
Author-email: justquick@gmail.com
License: BSD
Project-URL: Documentation, https://pynacl-cellar.readthedocs.io/
Project-URL: Source, https://github.com/justquick/salt-cellar
Project-URL: Bug Tracker, https://github.com/justquick/salt-cellar/issues
Classifier: Development Status :: 4 - Beta
Classifier: Programming Language :: Python :: 3
Classifier: License :: OSI Approved :: BSD License
Classifier: Operating System :: OS Independent
Classifier: Environment :: Console
Requires-Python: >=3.6
